cmfo/__init__.py
cmfo/bridge.py
cmfo/cli.py
cmfo/compression.py
cmfo/server.py
cmfo/vis.py
cmfo/core/__init__.py
cmfo/core/api.py
cmfo/core/gamma_phi.py
cmfo/core/phi_math.py
cmfo/core/t7_tensor.py
cmfo/layers/__init__.py
cmfo/layers/attention.py
cmfo/layers/linear.py
cmfo/logic/__init__.py
cmfo/logic/phi_logic.py
cmfo-1.1.1.dist-info/licenses/LICENSE.txt
cmfo-1.1.1.dist-info/METADATA
cmfo-1.1.1.dist-info/WHEEL
cmfo-1.1.1.dist-info/entry_points.txt
cmfo-1.1.1.dist-info/top_level.txt
cmfo-1.1.1.dist-info/RECORD
