Metadata-Version: 2.4
Name: cmfo
Version: 1.1.1
Summary: Fractal Universal Computation Engine
Home-page: https://github.com/1JONMONTERV/CMFO-COMPUTACION-FRACTAL-
Author: Jonathan Montero Viques
Author-email: Jonathan Montero Viques <jesuslocopor@gmail.com>
License: MIT
Project-URL: Homepage, https://1jonmonterv.github.io/CMFO-COMPUTACION-FRACTAL-/
Project-URL: Repository, https://github.com/1JONMONTERV/CMFO-COMPUTACION-FRACTAL-
Keywords: fractal,compute,deterministic,tensor7,ai,optimization,aerospace,science,formal-methods,geometry,cmfo,phi-manifold,quantum
Classifier: Development Status :: 5 - Production/Stable
Classifier: Intended Audience :: Science/Research
Classifier: Intended Audience :: Developers
Classifier: License :: OSI Approved :: MIT License
Classifier: Programming Language :: Python :: 3
Classifier: Programming Language :: Python :: 3.9
Classifier: Programming Language :: Python :: 3.10
Classifier: Programming Language :: Python :: 3.11
Classifier: Programming Language :: Python :: 3.12
Classifier: Topic :: Scientific/Engineering :: Artificial Intelligence
Classifier: Topic :: Scientific/Engineering :: Mathematics
Classifier: Topic :: Scientific/Engineering :: Physics
Requires-Python: >=3.9
License-File: LICENSE.txt
Requires-Dist: numpy>=1.20
Provides-Extra: cuda
Requires-Dist: cupy>=10.0; extra == "cuda"
Provides-Extra: dev
Requires-Dist: pytest>=7.0; extra == "dev"
Requires-Dist: black>=22.0; extra == "dev"
Requires-Dist: mypy>=0.990; extra == "dev"
Requires-Dist: build>=0.10; extra == "dev"
Provides-Extra: docs
Requires-Dist: sphinx>=5.0; extra == "docs"
Requires-Dist: sphinx-rtd-theme>=1.0; extra == "docs"
Dynamic: author
Dynamic: home-page
Dynamic: license-file
Dynamic: requires-python
